seismic_zfp/__init__.py
seismic_zfp/accessors.py
seismic_zfp/cli.py
seismic_zfp/conversion.py
seismic_zfp/conversion_utils.py
seismic_zfp/cropping.py
seismic_zfp/headers.py
seismic_zfp/loader.py
seismic_zfp/open.py
seismic_zfp/read.py
seismic_zfp/segyio_emulator.py
seismic_zfp/seismicfile.py
seismic_zfp/sgz_xarray.py
seismic_zfp/sgzconstants.py
seismic_zfp/tools.py
seismic_zfp/utils.py
seismic_zfp/version.py
seismic_zfp-0.4.3.dist-info/licenses/LICENSE.md
seismic_zfp-0.4.3.dist-info/METADATA
seismic_zfp-0.4.3.dist-info/WHEEL
seismic_zfp-0.4.3.dist-info/entry_points.txt
seismic_zfp-0.4.3.dist-info/top_level.txt
seismic_zfp-0.4.3.dist-info/RECORD
