Metadata-Version: 2.4
Name: seismic-zfp
Version: 0.4.3
Summary: Compress and decompress seismic data
Home-page: https://github.com/equinor/seismic-zfp
Author: equinor
License: LGPL-3.0
License-File: LICENSE.md
Requires-Dist: numpy
Requires-Dist: segyio
Requires-Dist: zfpy
Requires-Dist: psutil
Requires-Dist: click
Provides-Extra: zgy
Requires-Dist: pyzgy; extra == "zgy"
Provides-Extra: vds
Requires-Dist: pyvds; extra == "vds"
Provides-Extra: xr
Requires-Dist: xarray>=0.20.2; extra == "xr"
Provides-Extra: azure
Requires-Dist: azure-storage-blob; extra == "azure"
Dynamic: author
Dynamic: description
Dynamic: description-content-type
Dynamic: home-page
Dynamic: license
Dynamic: license-file
Dynamic: provides-extra
Dynamic: requires-dist
Dynamic: summary
